hxnfly/README
hxnfly/__init__.py
hxnfly/_version.py
hxnfly/bs.py
hxnfly/fly.py
hxnfly/fly1d.py
hxnfly/fly2d.py
hxnfly/fly_diff.py
hxnfly/fly_mll.py
hxnfly/fly_zp.py
hxnfly/hxn_fly.py
hxnfly/log.py
hxnfly/mds_util.py
hxnfly/object_plans.py
hxnfly/plot.py
hxnfly/ppmac_util.py
hxnfly/callbacks/__init__.py
hxnfly/callbacks/cross.py
hxnfly/callbacks/flydata.py
hxnfly/callbacks/liveimage.py
hxnfly/callbacks/liveplot.py
hxnfly/callbacks/roiplot.py
hxnfly/callbacks/table.py
hxnfly/scripts/__init__.py
hxnfly/scripts/cancel.txt
hxnfly/scripts/fly1d.txt
hxnfly/scripts/notes.txt
hxnfly/scripts/soft_1d.txt
hxnfly/scripts/soft_2d.txt
hxnfly/scripts/soft_2d_pyramid.txt
hxnfly/scripts/soft_gather.txt
hxnfly-0.0.12.dist-info/licenses/LICENSE
hxnfly-0.0.12.dist-info/METADATA
hxnfly-0.0.12.dist-info/WHEEL
hxnfly-0.0.12.dist-info/top_level.txt
hxnfly-0.0.12.dist-info/RECORD
